aiocorenlp/__init__.py
aiocorenlp/async_corenlp_server.py
aiocorenlp/async_corenlp_socket.py
aiocorenlp/async_ner_server.py
aiocorenlp/async_pos_server.py
aiocorenlp/version.py
aiocorenlp-1.0.2.dist-info/LICENSE.md
aiocorenlp-1.0.2.dist-info/METADATA
aiocorenlp-1.0.2.dist-info/WHEEL
aiocorenlp-1.0.2.dist-info/top_level.txt
aiocorenlp-1.0.2.dist-info/RECORD
